{"site":{"title":"Eco template","description":"épicerie des villages  comminges saint pé d ardet ambulant","enableMobile":true,"publicationPath":{"absPath":"/ce/github/get/test-github","size":0,"modified":"2020-09-01T21:17:08Z","name":"test-github","isDir":true,"mime":"application/git-repo","folder":"","path":"/test-github/master","service":"github","url":"https://editor.silex.me/github/get//test-github/master"},"websiteUrl":"www.lepiceriedesvillages.fr","faviconPath":null,"thumbnailSocialPath":null,"descriptionSocial":null,"titleSocial":null,"lang":"fr","width":980,"headUser":"","headStyle":"","headScript":"","hostingProvider":"ghpages","twitterSocial":null,"dataSources":{},"fonts":[{"family":"'Roboto', sans-serif","href":"https://fonts.googleapis.com/css?family=Roboto"},{"family":"Great Vibes","href":"https://fonts.googleapis.com/css?family=Great%20Vibes"}],"styles":{"all-style":{"className":"all-style","templateName":"text","displayName":"All Style","styles":{"desktop":{"normal":{"className":"all-style","pseudoClass":"normal","All":{"font-family":"'Roboto', sans-serif","font-size":"14px","line-height":"2"},"Link":{"color":"#000000","font-weight":"","text-decoration":"none"},"Heading2":{"font-weight":"normal"},"Heading1":{"font-variant":"small-caps","font-weight":"900","font-style":"italic"},"Paragraph":{"text-align":"center","font-size":"22px"}}}}},"nav":{"className":"nav","templateName":"text","displayName":"nav","styles":{"desktop":{"normal":{"className":"nav","pseudoClass":"normal","All":{"text-align":"center"},"Active":{"background-color":"#47c1d9"},"Link":{"color":"#000000","text-decoration":"none"}}}}},"header":{"className":"header","templateName":"text","displayName":"header","styles":{"desktop":{"normal":{"templateName":"text","className":"header","pseudoClass":"normal","All":{"word-spacing":"","text-align":"right"},"Link":{"text-decoration":"none"},"Active":{"background-color":"","color":"#0099FF"}}}}},"footer":{"className":"footer","templateName":"text","displayName":"footer","styles":{"desktop":{"normal":{"templateName":"text","className":"footer","pseudoClass":"normal","Link":{"color":"#0099FF"}}}}},"button":{"className":"button","templateName":"text","displayName":"button","styles":{"desktop":{"normal":{"className":"button","pseudoClass":"normal","Link":{},"All":{"text-align":"center","color":"#ffffff"}}}}},"captions":{"className":"captions","templateName":"text","displayName":"captions","styles":{"desktop":{"normal":{"className":"captions","pseudoClass":"normal","All":{"text-align":"center","font-style":"normal"},"Heading1":{"font-size":"0","gradient":{"colors":[{}]},"font-weight":"800"}}}}},"hamburger-menu":{"className":"hamburger-menu","templateName":"text","displayName":"Hamburger menu","styles":{"desktop":{"normal":{"className":"hamburger-menu","pseudoClass":"normal"}},"mobile":{"normal":{"templateName":"text","className":"hamburger-menu","pseudoClass":"normal","All":{"font-size":"1.5em"},"UnorderedList":{"list-style-type":"none","text-indent":"10px","line-height":"2"},"Active":{"color":"#0099FF"}}}}}},"isTemplate":false,"file":{"absPath":"/ce/github/get/test-github/master/editable.html","size":37657,"modified":"2020-09-05T18:30:43Z","name":"editable.html","isDir":false,"mime":"text/html","folder":"test-github/master","path":"test-github/master/editable.html","service":"github","url":"https://editor.silex.me/ce/github/get/test-github/master/editable.html"},"prodotypeDependencies":{}},"pages":[{"id":"page-home","displayName":"Home","link":{"linkType":"LinkTypePage","href":"#!page-home"},"canDelete":true,"canProperties":true,"canMove":true,"canRename":true,"opened":false},{"id":"page-products","displayName":"Products","link":{"linkType":"LinkTypePage","href":"#!page-products"},"canDelete":true,"canProperties":true,"canMove":true,"canRename":true,"opened":false},{"id":"page-about","displayName":"About","link":{"linkType":"LinkTypePage","href":"#!page-about"},"canDelete":true,"canProperties":true,"canMove":true,"canRename":true,"opened":false},{"id":"page-contact","displayName":"Contact","link":{"linkType":"LinkTypePage","href":"#!page-contact"},"canDelete":true,"canProperties":true,"canMove":true,"canRename":true,"opened":false}],"elements":[{"id":"body-initial","pageNames":[],"classList":[],"type":"container-element","isSectionContent":false,"title":"","alt":null,"children":["silex-id-1483139730465-7","silex-id-1483139563582-5","silex-id-1483139324559-3","silex-id-1483140114350-8","silex-id-1492633712778-6","silex-id-1492633694354-4","silex-id-1483139189898-1"],"link":null,"enableEdit":false,"enableDrag":false,"enableDrop":true,"enableResize":{"top":false,"bottom":false,"left":false,"right":false},"selected":false,"useMinHeight":true,"visibility":{"desktop":true,"mobile":true},"style":{"desktop":{"position":"static"},"mobile":{}},"data":{"component":null},"innerHtml":""},{"id":"silex-id-1483139730465-7","pageNames":[],"classList":["website-min-width"],"type":"section-element","isSectionContent":false,"title":"","alt":null,"children":["silex-id-1483139730465-6"],"link":null,"enableEdit":false,"enableDrag":true,"enableDrop":true,"enableResize":{"top":false,"bottom":false,"left":false,"right":false},"selected":false,"useMinHeight":true,"visibility":{"desktop":true,"mobile":true},"style":{"desktop":{"background-color":"rgba(255,233,185,1)","background-image":"url(../../../../../libs/templates/silex-templates/eco1/assets/seamless_paper_texture.png)","border-width":"0 0 1px 0 ","border-style":"groove","position":"static","margin-top":"-1px"},"mobile":{}},"data":{"component":null},"innerHtml":""},{"id":"silex-id-1483139730465-6","pageNames":[],"classList":["website-width"],"type":"container-element","isSectionContent":true,"title":"","alt":null,"children":["silex-id-1552773751232-5","silex-id-1552773787501-6","silex-id-1598991359171-0","silex-id-1439156722322-45"],"link":null,"enableEdit":false,"enableDrag":false,"enableDrop":true,"enableResize":{"top":true,"bottom":true,"left":true,"right":true},"selected":false,"useMinHeight":true,"visibility":{"desktop":true,"mobile":true},"style":{"desktop":{"background-color":"transparent","height":"139px","position":"relative","margin-left":"auto","margin-right":"auto"},"mobile":{}},"data":{"component":null},"innerHtml":""},{"id":"silex-id-1552773751232-5","pageNames":[],"classList":["hamburger-menu","prevent-auto-z-index"],"type":"text-element","isSectionContent":false,"title":"","alt":null,"children":[],"link":null,"enableEdit":true,"enableDrag":true,"enableDrop":false,"enableResize":{"top":false,"bottom":false,"left":false,"right":false},"selected":false,"useMinHeight":true,"visibility":{"desktop":false,"mobile":true},"style":{"desktop":{"width":"33px","background-color":"transparent","top":"100px","left":"686px","height":"27px","position":"absolute"},"mobile":{"left":"-12px","top":"2010px"}},"data":{"component":{"name":"hamburger1","templateName":"hamburger","data":{"fixed":false,"links":[{"properties":{"href":"#!page-home"},"text":"Home"},{"properties":{"href":"#!page-products"},"text":"Products"},{"properties":{"href":"#!page-about"},"text":"About"},{"properties":{"href":"#!page-contact"},"text":"Contact"}],"button-background-color":"#000000"}}},"innerHtml":"<style>\n/* nav */\n.hamburger-menu_1600017413946_554 {\n  position: absolute;\n  z-index: 20; /* above normal silex elements */\n}\n.silex-editor .hamburger-menu_1600017413946_554 nav {\n  left: -9999px;\n}\n.hamburger-menu_1600017413946_554 nav ul {\n  margin-top: 80px;\n}\n.hamburger-menu_1600017413946_554 nav {\n  opacity: 0; /* avoid flicker at start */\n  position: absolute;\n  background-color: #ededed;\n  transition: left 1s ease, height 0s ease 1s;\n  left: -300px;\n  width: 300px;\n  height: 20px\n}\n.hamburger-menu_1600017413946_554.open nav {\n  opacity: 1;\n  height: 100vh;\n  left: 0;\n  transition: left 1s ease, height 0s ease 0s;\n}\n\n.hamburger-menu_1600017413946_554 .nav-container {\n  z-index: 10;\n  position: absolute;\n}\n.hamburger-menu_1600017413946_554.open .nav-container {\n}\n\n/* hamburger button */\n.hamburger-menu_1600017413946_554 .hamburger-btn {\n    z-index: 20;\n    cursor: pointer;\n    position: absolute;\n}\n.hamburger-menu_1600017413946_554 .hamburger-btn span {\n    display: block;\n    width: 30px;\n    height: 5px;\n    margin-bottom: 3px;\n    position: relative;\n    background-color: #000000;\n    border: 1px solid #ffffff;\n    border-radius: 3px;\n    transition: border-color 0.1s ease-in,\n      opacity 0.1s ease-in,\n      transform 0.1s ease-in,\n      background 0.1s ease-in\n}\n\n.hamburger-menu_1600017413946_554.open .hamburger-btn span {\n    border-color: rgba(255, 255, 255, 0);\n}\n\n.hamburger-menu_1600017413946_554 .hamburger-btn span:first-child {\n    transform-origin: 4px -2px;\n}\n.hamburger-menu_1600017413946_554.open .hamburger-btn span:first-child {\n    transform: rotate(45deg) translate(7px, -4px);\n}\n\n.hamburger-menu_1600017413946_554.open .hamburger-btn span:nth-last-child(2) {\n    opacity: 0;\n}\n\n.hamburger-menu_1600017413946_554 .hamburger-btn span:nth-child(3) {\n    transform-origin: -11px 4px;\n}\n.hamburger-menu_1600017413946_554.open .hamburger-btn span:nth-child(3) {\n    transform: rotate(-45deg) translate(0, 12px);\n}\n\n/* themes */\n\n\n</style>\n<!-- inspired by https://codepen.io/erikterwan/pen/EVzeRP -->\n<div class=\"hamburger-menu_1600017413946_554 closed\">\n    <div class=\"hamburger-btn \">\n      <span></span>\n      <span></span>\n      <span></span>\n    </div>\n    <div class=\"nav-container\">\n      <div class=\"prevent-scale\">\n        <nav role=\"navigation\" class=\"\">\n            <ul>\n            \n                <li><a\n                    \n                        href=\"#!page-home\"\n                    \n                >Home</a></li>\n            \n                <li><a\n                    \n                        href=\"#!page-products\"\n                    \n                >Products</a></li>\n            \n                <li><a\n                    \n                        href=\"#!page-about\"\n                    \n                >About</a></li>\n            \n                <li><a\n                    \n                        href=\"#!page-contact\"\n                    \n                >Contact</a></li>\n            \n            </ul>\n        </nav>\n      </div>\n  </div>\n</div>\n<script>\n(function() {\n  var isOpen = false;\n  function close() {\n    isOpen = false;\n    $('.hamburger-menu_1600017413946_554').removeClass('open');\n    $('.hamburger-menu_1600017413946_554').addClass('closed');\n  }\n  function open() {\n    isOpen = true;\n    $('.hamburger-menu_1600017413946_554').addClass('open');\n    $('.hamburger-menu_1600017413946_554').removeClass('closed');\n  }\n  function toggle() {\n    if(isOpen) close();\n    else open();\n  }\n  var silexElement = $('.hamburger-menu_1600017413946_554').closest('.editable-style');\n  function move(data) {\n    var offset = silexElement.offset();\n    $('.hamburger-menu_1600017413946_554 .nav-container').css({\n      'transform': 'translate(' + (data.scrollLeft - (offset.left/data.scale)) + 'px, ' + (data.scrollTop - (offset.top/data.scale)) + 'px)'\n    });\n  }\n  $('.hamburger-menu_1600017413946_554 .hamburger-btn').click(function() { toggle(); });\n  $(document).on('silex.scroll silex.resize', function(e) {\n    close();\n    move(window.silex);\n  });\n  close();\n})();\n</script>\n"},{"id":"silex-id-1552773787501-6","pageNames":[],"classList":[],"type":"container-element","isSectionContent":false,"title":"","alt":null,"children":[],"link":null,"enableEdit":false,"enableDrag":true,"enableDrop":true,"enableResize":{"top":true,"bottom":true,"left":true,"right":true},"selected":false,"useMinHeight":true,"visibility":{"desktop":false,"mobile":true},"style":{"desktop":{"width":"100px","background-color":"rgb(255, 255, 255)","top":"100px","left":"653px","height":"100px","position":"absolute"},"mobile":{"left":"386px","top":"59px","background-color":"transparent","width":"20px","height":"20px"}},"data":{"component":null},"innerHtml":""},{"id":"silex-id-1598991359171-0","pageNames":[],"classList":[],"type":"image-element","isSectionContent":false,"title":"","alt":"","children":[],"link":null,"enableEdit":true,"enableDrag":true,"enableDrop":false,"enableResize":{"top":true,"bottom":true,"left":true,"right":true},"selected":false,"useMinHeight":false,"visibility":{"desktop":true,"mobile":true},"style":{"desktop":{"width":"663px","top":"0px","left":"-100px","height":"137px","position":"absolute"},"mobile":{}},"data":{"component":null},"innerHtml":"<img src=\"../../site/master/eco1/logo-1.png\" class=\"\">"},{"id":"silex-id-1439156722322-45","pageNames":[],"classList":["nav","header"],"type":"text-element","isSectionContent":false,"title":"","alt":null,"children":[],"link":null,"enableEdit":true,"enableDrag":true,"enableDrop":false,"enableResize":{"top":true,"bottom":true,"left":true,"right":true},"selected":false,"useMinHeight":true,"visibility":{"desktop":true,"mobile":false},"style":{"desktop":{"width":"391px","top":"58px","left":"590px","height":"132px","position":"absolute"},"mobile":{}},"data":{"component":null},"innerHtml":"\n                    <a href=\"#!page-home\" class=\"\"></a><p><a href=\"#!page-home\" class=\"\"><b>Accueil &nbsp;</b></a><b> &nbsp; &nbsp; &nbsp; &nbsp; &nbsp;&nbsp;</b><a href=\"#!page-products\" class=\"\"><b> Produits</b></a><b> &nbsp;&nbsp;&nbsp; &nbsp;&nbsp;&nbsp; &nbsp; </b><a href=\"#!page-contact\" class=\"\"><b>                        Contact&nbsp;</b></a></p>\n                    \n                "},{"id":"silex-id-1483139563582-5","pageNames":["page-home"],"classList":["website-min-width"],"type":"section-element","isSectionContent":false,"title":"","alt":null,"children":["silex-id-1483139563581-4"],"link":null,"enableEdit":false,"enableDrag":true,"enableDrop":true,"enableResize":{"top":false,"bottom":false,"left":false,"right":false},"selected":false,"useMinHeight":true,"visibility":{"desktop":true,"mobile":true},"style":{"desktop":{"min-width":"980px","background-color":"rgba(205,186,152,1)","background-image":"","position":"static","margin-top":"-1px"},"mobile":{"top":"200px","left":"0px"}},"data":{"component":null},"innerHtml":""},{"id":"silex-id-1483139563581-4","pageNames":[],"classList":["website-width"],"type":"container-element","isSectionContent":true,"title":"","alt":null,"children":["silex-id-1598992238379-2","silex-id-1439156722120-43","silex-id-1598993293541-3"],"link":null,"enableEdit":false,"enableDrag":false,"enableDrop":true,"enableResize":{"top":true,"bottom":true,"left":true,"right":true},"selected":false,"useMinHeight":true,"visibility":{"desktop":true,"mobile":true},"style":{"desktop":{"background-color":"transparent","height":"503px","position":"relative","margin-left":"auto","margin-right":"auto"},"mobile":{"height":"657px"}},"data":{"component":null},"innerHtml":""},{"id":"silex-id-1598992238379-2","pageNames":[],"classList":[],"type":"image-element","isSectionContent":false,"title":"","alt":"","children":[],"link":null,"enableEdit":true,"enableDrag":true,"enableDrop":false,"enableResize":{"top":true,"bottom":true,"left":true,"right":true},"selected":false,"useMinHeight":false,"visibility":{"desktop":true,"mobile":true},"style":{"desktop":{"width":"369px","top":"0px","left":"563.0000305175781px","height":"508px","position":"absolute"},"mobile":{}},"data":{"component":null},"innerHtml":"<img src=\"../../site/master/eco1/0001.jpg\" class=\"\">"},{"id":"silex-id-1439156722120-43","pageNames":[],"classList":[],"type":"text-element","isSectionContent":false,"title":"","alt":null,"children":[],"link":null,"enableEdit":true,"enableDrag":true,"enableDrop":false,"enableResize":{"top":true,"bottom":true,"left":true,"right":true},"selected":false,"useMinHeight":true,"visibility":{"desktop":true,"mobile":true},"style":{"desktop":{"width":"619px","top":"-22px","left":"-60px","border-top-color":"rgb(0, 0, 0)","border-right-color":"rgb(0, 0, 0)","border-bottom-color":"rgb(0, 0, 0)","border-left-color":"rgb(0, 0, 0)","height":"457.433349609375px","position":"absolute"},"mobile":{"top":"251px","left":"11px","width":"423px","height":"199px"}},"data":{"component":null},"innerHtml":"\n                    <h2><b>L' épicerie des villages</b></h2><h2>\n                    </h2><h2>C 'est une sélection de produits de qualité et le plus souvent locaux.</h2><h2>C'est une tournée de petits marchés et de livraison de paniers en Frontignes et pays de Saint Béat.</h2><h2>Il est possible de passer commande par téléphone et par mail.</h2><h2><b><u><a href=\"http://eepurl.com/hcdNCP\">&nbsp;recevoir chaque semaine le bulletin de commande</a></u></b></h2><h2><br> </h2>\n                    \n                    \n                "},{"id":"silex-id-1598993293541-3","pageNames":[],"classList":[],"type":"text-element","isSectionContent":false,"title":"","alt":null,"children":[],"link":null,"enableEdit":true,"enableDrag":true,"enableDrop":false,"enableResize":{"top":true,"bottom":true,"left":true,"right":true},"selected":false,"useMinHeight":true,"visibility":{"desktop":true,"mobile":true},"style":{"desktop":{"width":"429px","top":"406px","left":"59px","height":"88px","position":"absolute"},"mobile":{}},"data":{"component":null},"innerHtml":"<p><a href=\"http://localhost/dolibarr/document.php?modulepart=ecm&amp;attachment=1&amp;file=bulletin%2Fbulletin+de+commande.xlsx\" linktype=\"LinkTypeExternal\">télécharger le bulletin de commande .pdf</a><a href=\"http://localhost/dolibarr/document.php?modulepart=ecm&amp;attachment=1&amp;file=bulletin%2Fbulletin+de+commande.pdf\"><br></a></p>"},{"id":"silex-id-1483139324559-3","pageNames":["page-home"],"classList":["website-min-width"],"type":"section-element","isSectionContent":false,"title":"","alt":null,"children":["silex-id-1483139324558-2"],"link":null,"enableEdit":false,"enableDrag":true,"enableDrop":true,"enableResize":{"top":false,"bottom":false,"left":false,"right":false},"selected":false,"useMinHeight":true,"visibility":{"desktop":true,"mobile":true},"style":{"desktop":{"background-color":"rgba(255,255,255,1)","min-width":"980px","background-image":"url(../../../../../libs/templates/silex-templates/eco1/assets/halftone.png)","position":"static","margin-top":"-1px"},"mobile":{"top":"832px","left":"0px"}},"data":{"component":null},"innerHtml":""},{"id":"silex-id-1483139324558-2","pageNames":[],"classList":["website-width"],"type":"container-element","isSectionContent":true,"title":"","alt":null,"children":["silex-id-1598993322980-4"],"link":null,"enableEdit":false,"enableDrag":false,"enableDrop":true,"enableResize":{"top":true,"bottom":true,"left":true,"right":true},"selected":false,"useMinHeight":true,"visibility":{"desktop":true,"mobile":true},"style":{"desktop":{"background-color":"transparent","height":"100px","position":"relative","margin-left":"auto","margin-right":"auto"},"mobile":{"height":"945px"}},"data":{"component":null},"innerHtml":""},{"id":"silex-id-1598993322980-4","pageNames":[],"classList":[],"type":"text-element","isSectionContent":false,"title":"","alt":null,"children":[],"link":null,"enableEdit":true,"enableDrag":true,"enableDrop":false,"enableResize":{"top":true,"bottom":true,"left":true,"right":true},"selected":false,"useMinHeight":true,"visibility":{"desktop":true,"mobile":true},"style":{"desktop":{"width":"457px","top":"-34px","left":"49px","height":"88px","position":"absolute"},"mobile":{}},"data":{"component":null},"innerHtml":"<p><a href=\"http://localhost/dolibarr/document.php?modulepart=ecm&amp;attachment=1&amp;file=bulletin%2Fbulletin+de+commande.pdf\" linktype=\"LinkTypeExternal\">télécharger le bulletin de commande . xlsx</a></p>"},{"id":"silex-id-1483140114350-8","pageNames":["page-contact"],"classList":["website-min-width"],"type":"section-element","isSectionContent":false,"title":"","alt":null,"children":["silex-id-1483140114351-9"],"link":null,"enableEdit":false,"enableDrag":true,"enableDrop":true,"enableResize":{"top":false,"bottom":false,"left":false,"right":false},"selected":false,"useMinHeight":true,"visibility":{"desktop":true,"mobile":true},"style":{"desktop":{"background-color":"rgba(255,255,255,1)","min-width":"980px","background-image":"url(../../../../../libs/templates/silex-templates/eco1/assets/halftone.png)","position":"static","margin-top":"-1px"},"mobile":{"top":"200px","left":"0px"}},"data":{"component":null},"innerHtml":""},{"id":"silex-id-1483140114351-9","pageNames":[],"classList":["website-width"],"type":"container-element","isSectionContent":true,"title":"","alt":null,"children":["silex-id-1548873044453-5","silex-id-1598995426166-6"],"link":null,"enableEdit":false,"enableDrag":false,"enableDrop":true,"enableResize":{"top":true,"bottom":true,"left":true,"right":true},"selected":false,"useMinHeight":true,"visibility":{"desktop":true,"mobile":true},"style":{"desktop":{"background-color":"transparent","height":"693px","position":"relative","margin-left":"auto","margin-right":"auto"},"mobile":{"height":"541px"}},"data":{"component":null},"innerHtml":""},{"id":"silex-id-1548873044453-5","pageNames":[],"classList":["silex-component-form","silex-element-content-full-height"],"type":"html-element","isSectionContent":false,"title":"","alt":null,"children":[],"link":null,"enableEdit":true,"enableDrag":true,"enableDrop":false,"enableResize":{"top":true,"bottom":true,"left":true,"right":true},"selected":false,"useMinHeight":false,"visibility":{"desktop":true,"mobile":true},"style":{"desktop":{"width":"396px","height":"400px","background-color":"transparent","top":"82px","left":"554px","position":"absolute"},"mobile":{}},"data":{"component":{"name":"form1","templateName":"form","data":{"sendTo":"contact@lepiceriedesvillages.fr"}}},"innerHtml":"<form id=\"id_1600017413968_298\" action=\"https://formspree.io/contact@lepiceriedesvillages.fr\" method=\"POST\" >\n  \n  <div>\n    <label for=\"field1\">Name</label>\n    <input type=\"text\" required id=\"field1\" name=\"field1\" placeholder=\"Your name\">\n  </div>\n  \n  \n  <div>\n    <label for=\"field2\">Your email adress</label>\n    <input type=\"text\" required id=\"field2\" name=\"field2\" placeholder=\"your@email.com\">\n  </div>\n  \n  \n  <div class=\"fill-vertical\">\n    <label for=\"field3\">Your message</label>\n    <textarea required id=\"field3\" name=\"field3\" placeholder=\"What you have to say\"></textarea>\n  </div>\n  \n  <input type=\"submit\" value=\"Send\">\n</form>\n<style>\n#id_1600017413968_298 input[type=text], select {\n    width: 100%;\n    padding: 12px 20px;\n    margin: 8px 0;\n    display: inline-block;\n    border: 1px solid #ccc;\n    border-radius: 3px;\n    box-sizing: border-box;\n}\n\n#id_1600017413968_298 input[type=submit] {\n    width: 100%;\n    background-color: #4CAF50;\n    color: #FFFFFF;\n    padding: 14px 20px;\n    margin: 8px 0;\n    border: 1px solid #4CAF50;\n    border-radius: 3px;\n    cursor: pointer;\n}\n#id_1600017413968_298 label {\n    color: #000000;\n}\n/* *************************** */\n/* resize the 3rd field\n   and fill the vertical space */\n#id_1600017413968_298 .fill-vertical {\n    flex: 1 1 auto;\n    display: flex;\n    flex-direction: column;\n}\n#id_1600017413968_298 .fill-vertical textarea {\n    flex: 1 1 auto;\n    width: 100%;\n    height: 150px;\n    padding: 12px 20px;\n    box-sizing: border-box;\n    border: 2px solid #ccc;\n    border-radius: 3px;\n    background-color: #f8f8f8;\n    font-size: 16px;\n    resize: none;\n}\n/* ************************ */\n#id_1600017413968_298 {\n    border-radius: 3px;\n    display: flex;\n    flex-direction: column;\n    justify-content: space-between;\n    height: 100%;\n}\n</style>\n\n"},{"id":"silex-id-1598995426166-6","pageNames":[],"classList":[],"type":"text-element","isSectionContent":false,"title":"","alt":null,"children":[],"link":null,"enableEdit":true,"enableDrag":true,"enableDrop":false,"enableResize":{"top":true,"bottom":true,"left":true,"right":true},"selected":false,"useMinHeight":true,"visibility":{"desktop":true,"mobile":true},"style":{"desktop":{"width":"527px","top":"96px","left":"-62px","height":"396px","position":"absolute"},"mobile":{}},"data":{"component":null},"innerHtml":"<p>L' Epicerie des villages</p><p>épicerie ambulante <br></p><p>en Frontignes et Pays de Saint Béat</p><p><br></p><p>contact@lepiceriedesvillages.fr</p><p>06 85 69 73 72<br></p><span class=\"_wysihtml-temp-caret-fix\" style=\"position: absolute; display: block; min-width: 1px; z-index: 99999;\">﻿</span>"},{"id":"silex-id-1492633712778-6","pageNames":["page-products"],"classList":["website-min-width"],"type":"section-element","isSectionContent":false,"title":"","alt":null,"children":["silex-id-1492633712777-5"],"link":null,"enableEdit":false,"enableDrag":true,"enableDrop":true,"enableResize":{"top":false,"bottom":false,"left":false,"right":false},"selected":false,"useMinHeight":true,"visibility":{"desktop":true,"mobile":true},"style":{"desktop":{"background-color":"rgba(255,255,255,1)","background-image":"url(../../../../../libs/templates/silex-templates/eco1/assets/halftone.png)","min-width":"980px","position":"static","margin-top":"-1px"},"mobile":{}},"data":{"component":null},"innerHtml":""},{"id":"silex-id-1492633712777-5","pageNames":[],"classList":["website-width"],"type":"container-element","isSectionContent":true,"title":"","alt":null,"children":["silex-id-1599310279082-2"],"link":null,"enableEdit":false,"enableDrag":false,"enableDrop":true,"enableResize":{"top":true,"bottom":true,"left":true,"right":true},"selected":false,"useMinHeight":true,"visibility":{"desktop":true,"mobile":true},"style":{"desktop":{"background-color":"","height":"1750px","position":"relative","margin-left":"auto","margin-right":"auto"},"mobile":{}},"data":{"component":null},"innerHtml":""},{"id":"silex-id-1599310279082-2","pageNames":[],"classList":[],"type":"image-element","isSectionContent":false,"title":"","alt":"","children":[],"link":null,"enableEdit":true,"enableDrag":true,"enableDrop":false,"enableResize":{"top":true,"bottom":true,"left":true,"right":true},"selected":false,"useMinHeight":false,"visibility":{"desktop":true,"mobile":true},"style":{"desktop":{"width":"2481px","top":"-0.0000152587890625px","left":"-126.00001525878906px","height":"3508px","position":"absolute"},"mobile":{}},"data":{"component":null},"innerHtml":"<img src=\"https://editor.silex.me/ce/github/get/test-github/master/assets/0002.jpg\" />"},{"id":"silex-id-1492633694354-4","pageNames":["page-about"],"classList":["website-min-width"],"type":"section-element","isSectionContent":false,"title":"","alt":null,"children":["silex-id-1492633694353-3"],"link":null,"enableEdit":false,"enableDrag":true,"enableDrop":true,"enableResize":{"top":false,"bottom":false,"left":false,"right":false},"selected":false,"useMinHeight":true,"visibility":{"desktop":true,"mobile":true},"style":{"desktop":{"background-color":"rgba(255,255,255,1)","background-image":"url(../../../../../libs/templates/silex-templates/eco1/assets/halftone.png)","position":"static","margin-top":"-1px"},"mobile":{}},"data":{"component":null},"innerHtml":""},{"id":"silex-id-1492633694353-3","pageNames":[],"classList":["website-width"],"type":"container-element","isSectionContent":true,"title":"","alt":null,"children":["silex-id-1492633737513-7"],"link":null,"enableEdit":false,"enableDrag":false,"enableDrop":true,"enableResize":{"top":true,"bottom":true,"left":true,"right":true},"selected":false,"useMinHeight":true,"visibility":{"desktop":true,"mobile":true},"style":{"desktop":{"background-color":"","height":"800px","position":"relative","margin-left":"auto","margin-right":"auto"},"mobile":{}},"data":{"component":null},"innerHtml":""},{"id":"silex-id-1492633737513-7","pageNames":[],"classList":[],"type":"text-element","isSectionContent":false,"title":"","alt":null,"children":[],"link":null,"enableEdit":true,"enableDrag":true,"enableDrop":false,"enableResize":{"top":true,"bottom":true,"left":true,"right":true},"selected":false,"useMinHeight":true,"visibility":{"desktop":true,"mobile":true},"style":{"desktop":{"width":"763px","top":"30px","left":"0px","height":"75px","position":"absolute"},"mobile":{"top":"11px","left":"11px","width":"423px","height":"520px"}},"data":{"component":null},"innerHtml":"\n                    <p class=\"normal\">\n                        <font size=\"4\">Nothing here yet... Can't wait to see your content !</font>\n                    </p>\n                "},{"id":"silex-id-1483139189898-1","pageNames":[],"classList":["website-min-width"],"type":"section-element","isSectionContent":false,"title":"","alt":null,"children":["silex-id-1483139189897-0"],"link":null,"enableEdit":false,"enableDrag":true,"enableDrop":true,"enableResize":{"top":false,"bottom":false,"left":false,"right":false},"selected":false,"useMinHeight":true,"visibility":{"desktop":true,"mobile":true},"style":{"desktop":{"background-color":"rgba(56,56,56,1)","min-width":"980px","background-image":"url(../../../../../libs/templates/silex-templates/eco1/assets/footer_lodyas.png)","position":"static","margin-top":"-1px"},"mobile":{"top":"1131px","left":"0px"}},"data":{"component":null},"innerHtml":""},{"id":"silex-id-1483139189897-0","pageNames":[],"classList":["website-width"],"type":"container-element","isSectionContent":true,"title":"","alt":null,"children":["silex-id-1439156720704-29","silex-id-1439156720502-27"],"link":null,"enableEdit":false,"enableDrag":false,"enableDrop":true,"enableResize":{"top":true,"bottom":true,"left":true,"right":true},"selected":false,"useMinHeight":true,"visibility":{"desktop":true,"mobile":true},"style":{"desktop":{"background-color":"transparent","height":"217px","position":"relative","margin-left":"auto","margin-right":"auto"},"mobile":{"height":"268px"}},"data":{"component":null},"innerHtml":""},{"id":"silex-id-1439156720704-29","pageNames":[],"classList":[],"type":"image-element","isSectionContent":false,"title":"","alt":"","children":[],"link":{"linkType":"LinkTypeExternal","href":"//www.silexlabs.org/"},"enableEdit":true,"enableDrag":true,"enableDrop":false,"enableResize":{"top":true,"bottom":true,"left":true,"right":true},"selected":false,"useMinHeight":false,"visibility":{"desktop":true,"mobile":true},"style":{"desktop":{"width":"265px","top":"28px","left":"0px","height":"79px","position":"absolute"},"mobile":{}},"data":{"component":null},"innerHtml":"<img class=\"\" src=\"../../../../../libs/templates/silex-templates/eco1/assets/logo-silexlabs.png\">\n            "},{"id":"silex-id-1439156720502-27","pageNames":[],"classList":["abel","footer"],"type":"text-element","isSectionContent":false,"title":"","alt":null,"children":[],"link":null,"enableEdit":true,"enableDrag":true,"enableDrop":false,"enableResize":{"top":true,"bottom":true,"left":true,"right":true},"selected":false,"useMinHeight":true,"visibility":{"desktop":true,"mobile":true},"style":{"desktop":{"width":"589px","top":"152px","left":"174px","background-color":"transparent","height":"34px","position":"absolute"},"mobile":{}},"data":{"component":null},"innerHtml":"\n                    <p style=\"text-align: center;\" class=\"normal\"><span style=\"color: rgb(255, 255, 255); font-size: small;\">Creative Commons template by <a href=\"http://lexoyo.me\">@lexoyo</a></span><span style=\"color: rgb(255, 255, 255); font-size: small;\">&nbsp; &nbsp; - &nbsp; &nbsp;Powered by <a href=\"http://www.silex.me\">Silex</a></span>\n                    </p>\n                "}]}